ansipants/__init__.py
ansipants/__main__.py
ansipants-0.2.dist-info/LICENSE
ansipants-0.2.dist-info/METADATA
ansipants-0.2.dist-info/WHEEL
ansipants-0.2.dist-info/top_level.txt
ansipants-0.2.dist-info/RECORD
