Metadata-Version: 2.1
Name: ansipants
Version: 0.2
Summary: Convert ANSI art to HTML
Home-page: https://github.com/demozoo/ansipants/
Author: Matt Westcott
Author-email: matthew@west.co.tt
License: BSD
Platform: UNKNOWN
Classifier: Development Status :: 4 - Beta
Classifier: Environment :: Console
Classifier: Intended Audience :: Developers
Classifier: Programming Language :: Python :: 3
Classifier: Topic :: Multimedia :: Graphics :: Graphics Conversion
Classifier: Topic :: Text Processing :: Markup :: HTML
Classifier: License :: OSI Approved :: BSD License
Classifier: Operating System :: OS Independent
Requires-Python: >=3.6
License-File: LICENSE
